automationBeamNgExportFix/__init__.py
automationBeamNgExportFix/__main__.py
automationBeamNgExportFix/exportFix.py
automationBeamNgExportFix/get_files.py
automationBeamNgExportFix-1.3.0.dist-info/LICENSE
automationBeamNgExportFix-1.3.0.dist-info/METADATA
automationBeamNgExportFix-1.3.0.dist-info/WHEEL
automationBeamNgExportFix-1.3.0.dist-info/top_level.txt
automationBeamNgExportFix-1.3.0.dist-info/RECORD
