Metadata-Version: 2.1
Name: automationBeamNgExportFix
Version: 1.3.0
Summary: Tool to fix overheating issues in Automation the Car Company Tycoon Game exports into BeamNG.drive
Author-email: Jonathan Pecar <jonathan.pecar@gmail.com>
License: MIT License        
Project-URL: Homepage, https://github.com/jonpecar/automationBeamNgExportFix
Classifier: License :: OSI Approved :: MIT License
Classifier: Programming Language :: Python
Classifier: Programming Language :: Python :: 3
Requires-Python: >=3.6
License-File: LICENSE
Provides-Extra: dev
Requires-Dist: bumpver ; extra == 'dev'
Requires-Dist: setuptools ; extra == 'dev'
